CHANGES.txt
MANIFEST.in
README.txt
setup.py
bin/thed
thed/__init__.py
thed.egg-info/PKG-INFO
thed.egg-info/SOURCES.txt
thed.egg-info/dependency_links.txt
thed.egg-info/entry_points.txt
thed.egg-info/not-zip-safe
thed.egg-info/requires.txt
thed.egg-info/top_level.txt
thed/api/__init__.py
thed/api/auth.py
thed/api/controllers.py
thed/api/decorators.py
thed/api/predicates.py
thed/api/requests.py
thed/api/resources.py
thed/api/responses.py
thed/commands/__init__.py
thed/commands/scaffolds.py
thed/db/__init__.py
thed/models/__init__.py
thed/scaffolds/__init__.py