Metadata-Version: 1.1
Name: thed
Version: 0.1.5
Summary: thed
Home-page: UNKNOWN
Author: Balanced
Author-email: dev+thed@balancedpayments.com
License: UNKNOWN
Platform: UNKNOWN
Classifier: Programming Language :: Python
